{
  "unversionedId": "Tutorials/Python SDK/meaning-sentiment",
  "id": "Tutorials/Python SDK/meaning-sentiment",
  "isDocsHomePage": false,
  "title": "Meaning Sentiment",
  "description": "Video",
  "source": "@site/docs/Tutorials/Python SDK/meaning-sentiment.md",
  "sourceDirName": "Tutorials/Python SDK",
  "slug": "/Tutorials/Python SDK/meaning-sentiment",
  "permalink": "/documentation/docs/next/Tutorials/Python SDK/meaning-sentiment",
  "tags": [],
  "version": "current",
  "sidebarPosition": 9,
  "frontMatter": {
    "sidebar_position": 9
  },
  "sidebar": "tutorialSidebar",
  "previous": {
    "title": "Word Sentiment",
    "permalink": "/documentation/docs/next/Tutorials/Python SDK/TextChunk/word-sentiment"
  },
  "next": {
    "title": "Meaning Emotion",
    "permalink": "/documentation/docs/next/Tutorials/Python SDK/meaning-emotion"
  }
}